PyStatsDist/Binomialdistribution.py
PyStatsDist/Gaussiandistribution.py
PyStatsDist/Generaldistribution.py
PyStatsDist/__init__.py
PyStatsDist-0.1.dist-info/DESCRIPTION.rst
PyStatsDist-0.1.dist-info/METADATA
PyStatsDist-0.1.dist-info/RECORD
PyStatsDist-0.1.dist-info/WHEEL
PyStatsDist-0.1.dist-info/metadata.json
PyStatsDist-0.1.dist-info/top_level.txt
