Metadata-Version: 2.0
Name: PyStatsDist
Version: 0.1
Summary: Gaussian distributions
Home-page: UNKNOWN
Author: UNKNOWN
Author-email: UNKNOWN
License: UNKNOWN
Platform: UNKNOWN
Classifier: License :: OSI Approved :: MIT License
Classifier: Programming Language :: Python :: 3
Requires-Dist: numpy
Requires-Dist: matplotlib
